[
  {
    "id": 9,
    "title_id": 14,
    "season": 1,
    "episode": 1,
    "name": "1 Серия",
    "qualities": [
      {
        "quality": "480p",
        "url": "https://myanimevost.com/save.php?file=MjQ2fDEtc2VyaXlhfDY5NDU4OTY4N3xWMGRYaFFNR3wy",
        "size_mb": null
      }
    ],
    "thumbnail_url": "https://v3.animevost-rf.com/anime.php?i=246",
    "duration": null,
    "created_at": "2025-12-24 17:00:24.622501"
  },
  {
    "id": 10,
    "title_id": 15,
    "season": 1,
    "episode": 1,
    "name": "1 Серия",
    "qualities": [
      {
        "quality": "480p",
        "url": "https://myanimevost.com/save.php?file=NTJ8MS1zZXJpeWF8MTIwNDg4NTk0NHxWMGRYaFFNR3wy",
        "size_mb": null
      }
    ],
    "thumbnail_url": "https://img.animerf.com/pic/52_logo.jpg",
    "duration": null,
    "created_at": "2025-12-24 17:03:58.883335"
  },
  {
    "id": 11,
    "title_id": 16,
    "season": 1,
    "episode": 1,
    "name": "1 Серия",
    "qualities": [
      {
        "quality": "720p",
        "url": "https://theanimevost.com/save.php?file=MzM0N3wxLXNlcml5YXwxMDU1OTIzMzAwfEZaemN8Mw==",
        "size_mb": null
      }
    ],
    "thumbnail_url": "https://img.animerf.com/pic/3347_mini.jpg",
    "duration": null,
    "created_at": "2025-12-25 10:36:19.144041"
  },
  {
    "id": 12,
    "title_id": 17,
    "season": 1,
    "episode": 1,
    "name": "1 Серия",
    "qualities": [
      {
        "quality": "720p",
        "url": "https://theanimevost.com/save.php?file=MzE1MHwxLXNlcml5YXwyMTQ3NDIzMzQ3fEZaemN8Mw==",
        "size_mb": null
      }
    ],
    "thumbnail_url": "https://img.animerf.com/pic/3150_mini.jpg",
    "duration": null,
    "created_at": "2025-12-25 10:43:05.654822"
  }
]